{
    "metadata": {
        "cache_fetch_at": "2025-06-18T20:30:32.491312"
    },
    "data": {
        "table": [
            [
                {
                    "subject": "英文閱讀與寫作",
                    "counterpart": [
                        {
                            "participant": "李奇璋",
                            "url": "TB20.HTML"
                        }
                    ]
                },
                {
                    "subject": "各類文學選讀",
                    "counterpart": [
                        {
                            "participant": "殷念慈",
                            "url": "TA20.HTML"
                        }
                    ]
                },
                {
                    "subject": "數學乙",
                    "counterpart": [
                        {
                            "participant": "黃棨堯",
                            "url": "TC25.HTML"
                        }
                    ]
                },
                {
                    "subject": "空間資訊科技",
                    "counterpart": [
                        {
                            "participant": "陳麒丞",
                            "url": "TE04.HTML"
                        }
                    ]
                },
                {
                    "subject": "彈性-英文",
                    "counterpart": [
                        {
                            "participant": "Evan",
                            "url": "TB34.HTML"
                        }
                    ]
                },
                {
                    "subject": "民主政治與法律",
                    "counterpart": [
                        {
                            "participant": "阮雋絜",
                            "url": "TF05.HTML"
                        }
                    ]
                },
                {
                    "subject": "補強-歷史",
                    "counterpart": [
                        {
                            "participant": "楊秀蘭",
                            "url": "TD03.HTML"
                        }
                    ]
                },
                null
            ],
            [
                {
                    "subject": "體育",
                    "counterpart": [
                        {
                            "participant": "曾冠騰",
                            "url": "TK11.HTML"
                        }
                    ]
                },
                {
                    "subject": "補強-公民與社會",
                    "counterpart": [
                        {
                            "participant": "阮雋絜",
                            "url": "TF05.HTML"
                        }
                    ]
                },
                {
                    "subject": "英語聽講",
                    "counterpart": [
                        {
                            "participant": "李奇璋",
                            "url": "TB20.HTML"
                        }
                    ]
                },
                {
                    "subject": "英語聽講",
                    "counterpart": [
                        {
                            "participant": "李奇璋",
                            "url": "TB20.HTML"
                        }
                    ]
                },
                {
                    "subject": "各類文學選讀",
                    "counterpart": [
                        {
                            "participant": "殷念慈",
                            "url": "TA20.HTML"
                        }
                    ]
                },
                {
                    "subject": "數學乙",
                    "counterpart": [
                        {
                            "participant": "黃棨堯",
                            "url": "TC25.HTML"
                        }
                    ]
                },
                {
                    "subject": "科技、環境與藝術的歷史",
                    "counterpart": [
                        {
                            "participant": "楊秀蘭",
                            "url": "TD03.HTML"
                        }
                    ]
                },
                null
            ],
            [
                {
                    "subject": "美術",
                    "counterpart": [
                        {
                            "participant": "黃逸民",
                            "url": "TJ08.HTML"
                        }
                    ]
                },
                {
                    "subject": "美術",
                    "counterpart": [
                        {
                            "participant": "黃逸民",
                            "url": "TJ08.HTML"
                        }
                    ]
                },
                {
                    "subject": "空間資訊科技",
                    "counterpart": [
                        {
                            "participant": "陳麒丞",
                            "url": "TE04.HTML"
                        }
                    ]
                },
                {
                    "subject": "彈性-國文",
                    "counterpart": [
                        {
                            "participant": "殷念慈",
                            "url": "TA20.HTML"
                        }
                    ]
                },
                {
                    "subject": "民主政治與法律",
                    "counterpart": [
                        {
                            "participant": "阮雋絜",
                            "url": "TF05.HTML"
                        }
                    ]
                },
                {
                    "subject": "健康與護理",
                    "counterpart": [
                        {
                            "participant": "黃凱羚",
                            "url": "TJ21.HTML"
                        }
                    ]
                },
                {
                    "subject": "彈性學習時間",
                    "counterpart": null
                },
                null
            ],
            [
                {
                    "subject": "團體活動時間",
                    "counterpart": [
                        {
                            "participant": "李奇璋",
                            "url": "TB20.HTML"
                        }
                    ]
                },
                {
                    "subject": "團體活動時間",
                    "counterpart": [
                        {
                            "participant": "李奇璋",
                            "url": "TB20.HTML"
                        }
                    ]
                },
                {
                    "subject": "科技、環境與藝術的歷史",
                    "counterpart": [
                        {
                            "participant": "楊秀蘭",
                            "url": "TD03.HTML"
                        }
                    ]
                },
                {
                    "subject": "音樂",
                    "counterpart": [
                        {
                            "participant": "王理俐",
                            "url": "TJ05.HTML"
                        }
                    ]
                },
                {
                    "subject": "體育",
                    "counterpart": [
                        {
                            "participant": "曾冠騰",
                            "url": "TK11.HTML"
                        }
                    ]
                },
                {
                    "subject": "空間資訊科技",
                    "counterpart": [
                        {
                            "participant": "陳麒丞",
                            "url": "TE04.HTML"
                        }
                    ]
                },
                {
                    "subject": "科技、環境與藝術的歷史",
                    "counterpart": [
                        {
                            "participant": "楊秀蘭",
                            "url": "TD03.HTML"
                        }
                    ]
                },
                null
            ],
            [
                {
                    "subject": "語文表達與傳播應用",
                    "counterpart": [
                        {
                            "participant": "殷念慈",
                            "url": "TA20.HTML"
                        }
                    ]
                },
                {
                    "subject": "語文表達與傳播應用",
                    "counterpart": [
                        {
                            "participant": "殷念慈",
                            "url": "TA20.HTML"
                        }
                    ]
                },
                {
                    "subject": "數學乙",
                    "counterpart": [
                        {
                            "participant": "黃棨堯",
                            "url": "TC25.HTML"
                        }
                    ]
                },
                {
                    "subject": "數學乙",
                    "counterpart": [
                        {
                            "participant": "黃棨堯",
                            "url": "TC25.HTML"
                        }
                    ]
                },
                {
                    "subject": "英文閱讀與寫作",
                    "counterpart": [
                        {
                            "participant": "李奇璋",
                            "url": "TB20.HTML"
                        }
                    ]
                },
                {
                    "subject": "民主政治與法律",
                    "counterpart": [
                        {
                            "participant": "阮雋絜",
                            "url": "TF05.HTML"
                        }
                    ]
                },
                {
                    "subject": "補強-地理",
                    "counterpart": [
                        {
                            "participant": "陳麒丞",
                            "url": "TE04.HTML"
                        }
                    ]
                },
                null
            ]
        ],
        "periods": {
            "第一節": [
                "08:00",
                "08:50"
            ],
            "第二節": [
                "09:00",
                "09:50"
            ],
            "第三節": [
                "10:10",
                "11:00"
            ],
            "第四節": [
                "11:10",
                "12:00"
            ],
            "第五節": [
                "13:10",
                "14:00"
            ],
            "第六節": [
                "14:10",
                "15:00"
            ],
            "第七節": [
                "15:10",
                "16:00"
            ],
            "第八節": [
                "16:10",
                "17:00"
            ]
        },
        "type": "class",
        "target": "302",
        "target_url": "C101302.html",
        "last_update": "2025/02/03 18:59:34"
    }
}